zk/__init__.py
zk/attendance.py
zk/base.py
zk/const.py
zk/exception.py
zk/finger.py
zk/user.py
pyzk_new-0.9.1.dist-info/LICENSE
pyzk_new-0.9.1.dist-info/LICENSE.txt
pyzk_new-0.9.1.dist-info/METADATA
pyzk_new-0.9.1.dist-info/WHEEL
pyzk_new-0.9.1.dist-info/top_level.txt
pyzk_new-0.9.1.dist-info/RECORD
